{
  "scorerVersion": "ledger-v4-scorer-1",
  "cohorts": {
    "tactical_benchmark_fixed": {
      "1d": {
        "n": 63,
        "hitRate": 0.6508,
        "brierMean": 0.1897,
        "rpsMean": 0.1643
      },
      "3d": {
        "n": 42,
        "hitRate": 0.4286,
        "brierMean": 0.2255,
        "rpsMean": 0.214
      },
      "5d": {
        "n": 28,
        "hitRate": 0.5,
        "brierMean": 0.2183,
        "rpsMean": 0.2074
      }
    },
    "experimental_cohort": {
      "1d": {
        "n": 9,
        "hitRate": 0.2222,
        "brierMean": 0.2609,
        "rpsMean": 0.279
      },
      "3d": {
        "n": 6,
        "hitRate": 0.3333,
        "brierMean": 0.2583,
        "rpsMean": 0.2581
      },
      "5d": {
        "n": 4,
        "hitRate": 0.0,
        "brierMean": 0.3179,
        "rpsMean": 0.3519
      }
    },
    "regime_sensor_fixed": {
      "1d": {
        "n": 90,
        "hitRate": 0.8778,
        "brierMean": 0.1484,
        "rpsMean": 0.0989
      },
      "3d": {
        "n": 55,
        "hitRate": 0.6,
        "brierMean": 0.1947,
        "rpsMean": 0.1658
      },
      "5d": {
        "n": 42,
        "hitRate": 0.4524,
        "brierMean": 0.2191,
        "rpsMean": 0.201
      }
    }
  },
  "epochId": "calibration_v1",
  "status": "dry_run",
  "updated": "2026-07-08",
  "recorded": 20,
  "scored": 59,
  "held": 0,
  "totalRows": 182,
  "tradingDays": 10,
  "noteJa": "v4のparallel dry-run(本番ヘッドラインではない)。v3とは別ディレクトリ。市場別クロックでJPを採点、US/cryptoは正しい時刻のジョブ実装まで保留。"
}