{
 "updated": "2026-07-17",
 "engineVersion": "ledger-v3",
 "overall": {
  "days": 16,
  "n": 224,
  "hitRate": 0.777,
  "brierMean": 0.4912
 },
 "byPosture": {
  "EVENT_WAIT": {
   "days": 5,
   "n": 62,
   "hitRate": 0.71,
   "brierMean": 0.519
  },
  "MIXED": {
   "days": 4,
   "n": 50,
   "hitRate": 0.78,
   "brierMean": 0.4829
  },
  "CAUTIOUS": {
   "days": 5,
   "n": 80,
   "hitRate": 0.825,
   "brierMean": 0.4766
  },
  "RISK_ON": {
   "days": 2,
   "n": 32,
   "hitRate": 0.781,
   "brierMean": 0.4867
  }
 },
 "byVixZone": {
  "elevated": {
   "days": 1,
   "n": 7,
   "hitRate": 0.571,
   "brierMean": 0.52
  },
  "normal": {
   "days": 15,
   "n": 217,
   "hitRate": 0.783,
   "brierMean": 0.4903
  }
 },
 "aiDirectional": {
  "n": 0,
  "hits": 0,
  "hitRate": null
 },
 "classes": {
  "n": 152,
  "hits": 129,
  "hitRate": 0.849,
  "brierMean": 0.4528,
  "byClass": {
   "GOLD": {
    "n": 16,
    "hits": 13,
    "hitRate": 0.812
   },
   "BOND": {
    "n": 16,
    "hits": 16,
    "hitRate": 1.0
   },
   "REIT": {
    "n": 16,
    "hits": 15,
    "hitRate": 0.938
   },
   "CRYPTO_BTC": {
    "n": 16,
    "hits": 12,
    "hitRate": 0.75
   },
   "CRYPTO_ETH": {
    "n": 16,
    "hits": 9,
    "hitRate": 0.562
   },
   "US_BROAD": {
    "n": 12,
    "hits": 12,
    "hitRate": 1.0
   },
   "US_GROWTH": {
    "n": 12,
    "hits": 11,
    "hitRate": 0.917
   },
   "SMALL_CAPS": {
    "n": 12,
    "hits": 12,
    "hitRate": 1.0
   },
   "TECH": {
    "n": 12,
    "hits": 6,
    "hitRate": 0.5
   },
   "DEFENSIVE": {
    "n": 12,
    "hits": 11,
    "hitRate": 0.917
   },
   "CREDIT": {
    "n": 12,
    "hits": 12,
    "hitRate": 1.0
   }
  }
 },
 "posture": {
  "n": 5,
  "hits": 0,
  "hitRate": 0.0,
  "byPosture": {
   "EVENT_WAIT": {
    "n": 3,
    "hits": 0,
    "hitRate": 0.0
   },
   "RISK_ON": {
    "n": 2,
    "hits": 0,
    "hitRate": 0.0
   }
  }
 },
 "layers": {
  "layer1": {
   "byHorizon": {
    "1": {
     "n": 160,
     "hits": 142,
     "hitRate": 0.887,
     "brierMean": 0.435,
     "byMember": {
      "TLT": {
       "n": 16,
       "hits": 16,
       "hitRate": 1.0
      },
      "GLD": {
       "n": 16,
       "hits": 13,
       "hitRate": 0.812
      },
      "BTC": {
       "n": 16,
       "hits": 15,
       "hitRate": 0.938
      },
      "SMH": {
       "n": 13,
       "hits": 3,
       "hitRate": 0.231
      },
      "XLF": {
       "n": 13,
       "hits": 13,
       "hitRate": 1.0
      },
      "XLE": {
       "n": 13,
       "hits": 11,
       "hitRate": 0.846
      },
      "LQD": {
       "n": 13,
       "hits": 13,
       "hitRate": 1.0
      },
      "SPY": {
       "n": 12,
       "hits": 12,
       "hitRate": 1.0
      },
      "QQQ": {
       "n": 12,
       "hits": 11,
       "hitRate": 0.917
      },
      "IWM": {
       "n": 12,
       "hits": 12,
       "hitRate": 1.0
      },
      "XLU": {
       "n": 12,
       "hits": 11,
       "hitRate": 0.917
      },
      "HYG": {
       "n": 12,
       "hits": 12,
       "hitRate": 1.0
      }
     },
     "days": 16
    },
    "3": {
     "n": 146,
     "hits": 116,
     "hitRate": 0.795,
     "brierMean": 0.4855,
     "byMember": {
      "SPY": {
       "n": 12,
       "hits": 11,
       "hitRate": 0.917
      },
      "QQQ": {
       "n": 12,
       "hits": 10,
       "hitRate": 0.833
      },
      "IWM": {
       "n": 12,
       "hits": 12,
       "hitRate": 1.0
      },
      "XLU": {
       "n": 12,
       "hits": 11,
       "hitRate": 0.917
      },
      "TLT": {
       "n": 14,
       "hits": 12,
       "hitRate": 0.857
      },
      "HYG": {
       "n": 12,
       "hits": 12,
       "hitRate": 1.0
      },
      "GLD": {
       "n": 14,
       "hits": 10,
       "hitRate": 0.714
      },
      "BTC": {
       "n": 14,
       "hits": 10,
       "hitRate": 0.714
      },
      "SMH": {
       "n": 11,
       "hits": 5,
       "hitRate": 0.455
      },
      "XLF": {
       "n": 11,
       "hits": 7,
       "hitRate": 0.636
      },
      "XLE": {
       "n": 11,
       "hits": 5,
       "hitRate": 0.455
      },
      "LQD": {
       "n": 11,
       "hits": 11,
       "hitRate": 1.0
      }
     },
     "days": 14
    },
    "5": {
     "n": 126,
     "hits": 88,
     "hitRate": 0.698,
     "brierMean": 0.5429,
     "byMember": {
      "SPY": {
       "n": 10,
       "hits": 9,
       "hitRate": 0.9
      },
      "QQQ": {
       "n": 10,
       "hits": 8,
       "hitRate": 0.8
      },
      "IWM": {
       "n": 10,
       "hits": 10,
       "hitRate": 1.0
      },
      "XLU": {
       "n": 10,
       "hits": 10,
       "hitRate": 1.0
      },
      "TLT": {
       "n": 12,
       "hits": 7,
       "hitRate": 0.583
      },
      "HYG": {
       "n": 10,
       "hits": 10,
       "hitRate": 1.0
      },
      "GLD": {
       "n": 12,
       "hits": 6,
       "hitRate": 0.5
      },
      "BTC": {
       "n": 12,
       "hits": 6,
       "hitRate": 0.5
      },
      "SMH": {
       "n": 10,
       "hits": 3,
       "hitRate": 0.3
      },
      "XLF": {
       "n": 10,
       "hits": 5,
       "hitRate": 0.5
      },
      "XLE": {
       "n": 10,
       "hits": 4,
       "hitRate": 0.4
      },
      "LQD": {
       "n": 10,
       "hits": 10,
       "hitRate": 1.0
      }
     },
     "days": 12
    }
   }
  },
  "layer2": {
   "byHorizon": {
    "1": {
     "n": 64,
     "hits": 32,
     "hitRate": 0.5,
     "brierMean": 0.6317,
     "byMember": {
      "NVDA": {
       "n": 16,
       "hits": 10,
       "hitRate": 0.625
      },
      "AAPL": {
       "n": 16,
       "hits": 11,
       "hitRate": 0.688
      },
      "TSLA": {
       "n": 16,
       "hits": 7,
       "hitRate": 0.438
      },
      "META": {
       "n": 16,
       "hits": 4,
       "hitRate": 0.25
      }
     },
     "days": 16
    },
    "3": {
     "n": 56,
     "hits": 16,
     "hitRate": 0.286,
     "brierMean": 0.7412,
     "byMember": {
      "NVDA": {
       "n": 14,
       "hits": 5,
       "hitRate": 0.357
      },
      "AAPL": {
       "n": 14,
       "hits": 6,
       "hitRate": 0.429
      },
      "TSLA": {
       "n": 14,
       "hits": 2,
       "hitRate": 0.143
      },
      "META": {
       "n": 14,
       "hits": 3,
       "hitRate": 0.214
      }
     },
     "days": 14
    },
    "5": {
     "n": 48,
     "hits": 11,
     "hitRate": 0.229,
     "brierMean": 0.807,
     "byMember": {
      "NVDA": {
       "n": 12,
       "hits": 5,
       "hitRate": 0.417
      },
      "AAPL": {
       "n": 12,
       "hits": 3,
       "hitRate": 0.25
      },
      "TSLA": {
       "n": 12,
       "hits": 2,
       "hitRate": 0.167
      },
      "META": {
       "n": 12,
       "hits": 1,
       "hitRate": 0.083
      }
     },
     "days": 12
    }
   }
  },
  "layer3": {
   "byHorizon": {
    "1": {
     "n": 0,
     "hits": 0,
     "hitRate": null,
     "brierMean": null,
     "byMember": {},
     "days": 16
    },
    "3": {
     "n": 0,
     "hits": 0,
     "hitRate": null,
     "brierMean": null,
     "byMember": {},
     "days": 14
    },
    "5": {
     "n": 0,
     "hits": 0,
     "hitRate": null,
     "brierMean": null,
     "byMember": {},
     "days": 12
    }
   }
  }
 },
 "noteJa": "シナリオ分布のargmax的中率とBrierスコア(低いほど良い)。v3: 3層×1/3/5営業日ホライズン(Layer1=固定16センサー・bandPct=資産種別の日次σ単位)。成績は分類の校正度であり、将来の利益を保証しない。"
}