{
 "date": "2026-07-16",
 "asOf": "2026-07-16T09:22:10Z",
 "globalRegime": "CAUTIOUS",
 "jpIntradayOverlay": "RISK_OFF_WATCH",
 "holderRiskOverlay": "NONE",
 "activeCount": 5,
 "incidents": [
  {
   "symbol": "285A",
   "market": "JP",
   "assetName": "キオクシアホールディングス",
   "changePct": -15.03,
   "incidentType": "STOCK_SPECIFIC_BAD_NEWS",
   "severity": "critical",
   "actionOverride": "EXIT_WATCH",
   "isHeld": false,
   "ownerState": "watch",
   "causeBuckets": [
    {
     "cause": "STOCK_SPECIFIC_BAD_NEWS",
     "evidenceIds": [],
     "probability": 0.37
    },
    {
     "cause": "CAUSE_UNKNOWN_DOWNSIDE",
     "evidenceIds": [],
     "probability": 0.3
    },
    {
     "cause": "SECTOR_SELL_OFF",
     "evidenceIds": [],
     "probability": 0.26
    },
    {
     "cause": "MARKET_WIDE_SELL_OFF",
     "evidenceIds": [],
     "probability": 0.07
    }
   ],
   "reasonJa": "キオクシアホールディングスが-15.0%。個別の材料(悪材料の可能性・要確認)(次点: 原因未確認の下落)の可能性。 直近に個別材料(決算発表直後)があり下落と整合(内容は要確認・悪材料と断定はしない)。 ／ 原因確定なし。有力材料: 同業連動: 同業/テーマ3銘柄中2銘柄が同方向(ai_semis_cable)(発表時刻と値動きの時刻整合が未確認。)"
  },
  {
   "symbol": "5801",
   "market": "JP",
   "assetName": "古河電気工業",
   "changePct": -7.75,
   "incidentType": "STOCK_SPECIFIC_BAD_NEWS",
   "severity": "critical",
   "actionOverride": "EXIT_WATCH",
   "isHeld": false,
   "ownerState": "watch",
   "causeBuckets": [
    {
     "cause": "STOCK_SPECIFIC_BAD_NEWS",
     "evidenceIds": [],
     "probability": 0.37
    },
    {
     "cause": "CAUSE_UNKNOWN_DOWNSIDE",
     "evidenceIds": [],
     "probability": 0.3
    },
    {
     "cause": "SECTOR_SELL_OFF",
     "evidenceIds": [],
     "probability": 0.26
    },
    {
     "cause": "MARKET_WIDE_SELL_OFF",
     "evidenceIds": [],
     "probability": 0.07
    }
   ],
   "reasonJa": "古河電気工業が-7.8%。個別の材料(悪材料の可能性・要確認)(次点: 原因未確認の下落)の可能性。 直近に個別材料(決算発表直後)があり下落と整合(内容は要確認・悪材料と断定はしない)。 ／ 原因確定なし。有力材料: 同業連動: 同業/テーマ4銘柄中3銘柄が同方向(ai_semis_cable)(発表時刻と値動きの時刻整合が未確認。)"
  },
  {
   "symbol": "5803",
   "market": "JP",
   "assetName": "フジクラ",
   "changePct": -7.46,
   "incidentType": "STOCK_SPECIFIC_BAD_NEWS",
   "severity": "critical",
   "actionOverride": "EXIT_WATCH",
   "isHeld": false,
   "ownerState": "watch",
   "causeBuckets": [
    {
     "cause": "STOCK_SPECIFIC_BAD_NEWS",
     "evidenceIds": [],
     "probability": 0.37
    },
    {
     "cause": "CAUSE_UNKNOWN_DOWNSIDE",
     "evidenceIds": [],
     "probability": 0.3
    },
    {
     "cause": "SECTOR_SELL_OFF",
     "evidenceIds": [],
     "probability": 0.26
    },
    {
     "cause": "MARKET_WIDE_SELL_OFF",
     "evidenceIds": [],
     "probability": 0.07
    }
   ],
   "reasonJa": "フジクラが-7.5%。個別の材料(悪材料の可能性・要確認)(次点: 原因未確認の下落)の可能性。 直近に個別材料(決算発表直後)があり下落と整合(内容は要確認・悪材料と断定はしない)。 ／ 原因確定なし。有力材料: 同業連動: 同業/テーマ4銘柄中3銘柄が同方向(ai_semis_cable)(発表時刻と値動きの時刻整合が未確認。)"
  },
  {
   "symbol": "9984",
   "market": "JP",
   "assetName": "ソフトバンクグループ",
   "changePct": -6.27,
   "incidentType": "STOCK_SPECIFIC_BAD_NEWS",
   "severity": "critical",
   "actionOverride": "EXIT_WATCH",
   "isHeld": false,
   "ownerState": "watch",
   "causeBuckets": [
    {
     "cause": "STOCK_SPECIFIC_BAD_NEWS",
     "evidenceIds": [],
     "probability": 0.53
    },
    {
     "cause": "CAUSE_UNKNOWN_DOWNSIDE",
     "evidenceIds": [],
     "probability": 0.37
    },
    {
     "cause": "MARKET_WIDE_SELL_OFF",
     "evidenceIds": [],
     "probability": 0.1
    }
   ],
   "reasonJa": "ソフトバンクグループが-6.3%。個別の材料(悪材料の可能性・要確認)(次点: 原因未確認の下落)の可能性。 直近に個別材料(決算発表直後)があり下落と整合(内容は要確認・悪材料と断定はしない)。 ／ 原因確定なし。ただし有力候補: 直接ニュース: ソフトバンクグループ(株)【9984】：今の株価の理由は？値動きの背景をAIが解説 - Yahoo!ファイナンス(単一ソースのため裏取りが必要。市場反応との整合が未確認。)"
  },
  {
   "symbol": "6584",
   "market": "JP",
   "assetName": "三櫻工業",
   "changePct": -3.27,
   "incidentType": "STOCK_SPECIFIC_BAD_NEWS",
   "severity": "medium",
   "actionOverride": "REVIEW_REQUIRED",
   "isHeld": false,
   "ownerState": "watch",
   "causeBuckets": [
    {
     "cause": "STOCK_SPECIFIC_BAD_NEWS",
     "evidenceIds": [],
     "probability": 0.6
    },
    {
     "cause": "CAUSE_UNKNOWN_DOWNSIDE",
     "evidenceIds": [],
     "probability": 0.29
    },
    {
     "cause": "MARKET_WIDE_SELL_OFF",
     "evidenceIds": [],
     "probability": 0.11
    }
   ],
   "reasonJa": "三櫻工業が-3.3%。個別の材料(悪材料の可能性・要確認)(次点: 原因未確認の下落)の可能性。 直近に個別材料(決算発表直後)があり下落と整合(内容は要確認・悪材料と断定はしない)。 ／ 現時点で有力候補なし。確認済み: TDnet/公式イベント/日本語ニュース/C.A.O.S./マクロ。次に確認: 出来高・大口フローを確認・同業銘柄の値動きを確認"
  }
 ]
}